ckx_jokes/__init__.py
ckx_jokes/app.py
ckx_jokes/config.py
ckx_jokes/server.py
ckx_jokes/core/__init__.py
ckx_jokes/core/jokes.py
ckx_jokes/core/routes.py
ckx_jokes/server/__init__.py
ckx_jokes/server/config.py
ckx_jokes/server/core/__init__.py
ckx_jokes/server/core/jokes.py
ckx_jokes/server/core/routes.py
ckx_jokes-0.4.dist-info/licenses/LICENSE
ckx_jokes-0.4.dist-info/METADATA
ckx_jokes-0.4.dist-info/WHEEL
ckx_jokes-0.4.dist-info/entry_points.txt
ckx_jokes-0.4.dist-info/top_level.txt
ckx_jokes-0.4.dist-info/RECORD
