Metadata-Version: 2.4
Name: ckx-jokes
Version: 0.4
Summary: A Flask-based REST API for retrieving jokes with support for multiple categories and languages.
Home-page: https://pyjok-es.onrender.com/
Author: CryptoKingXavier
Author-email: cryptokingxavier001@gmail.com
License: MIT
Project-URL: Documentation, https://pypi.org/project/ckx-jokes/
Project-URL: Source, https://github.com/CryptoKingXavier/PyJok.Es/
Project-URL: Tracker, https://github.com/CryptoKingXavier/PyJok.Es/issues/
Keywords: python packaging cli utilities jokes
Classifier: Intended Audience :: Developers
Classifier: License :: OSI Approved :: MIT License
Classifier: Programming Language :: Python :: 3
Classifier: Programming Language :: Python :: 3.10
Classifier: Programming Language :: Python :: 3.11
Classifier: Programming Language :: Python :: 3.12
Classifier: Programming Language :: Python :: 3.13
Classifier: Operating System :: OS Independent
Classifier: Topic :: Software Development :: Libraries
Requires-Python: >=3.10
License-File: LICENSE
Requires-Dist: flask
Requires-Dist: wheel
Requires-Dist: pyjokes
Requires-Dist: ascii-magic
Requires-Dist: python-dotenv
Provides-Extra: dev
Requires-Dist: pytest; extra == "dev"
Requires-Dist: mypy; extra == "dev"
Requires-Dist: twine; extra == "dev"
Requires-Dist: snoop; extra == "dev"
Requires-Dist: gunicorn; extra == "dev"
Dynamic: author
Dynamic: author-email
Dynamic: classifier
Dynamic: description
Dynamic: description-content-type
Dynamic: home-page
Dynamic: keywords
Dynamic: license
Dynamic: license-file
Dynamic: project-url
Dynamic: provides-extra
Dynamic: requires-dist
Dynamic: requires-python
Dynamic: summary
